README.rst
setup.py
src/pyramid_tablib/__init__.py
src/pyramid_tablib/renderer.py
src/pyramid_tablib.egg-info/PKG-INFO
src/pyramid_tablib.egg-info/SOURCES.txt
src/pyramid_tablib.egg-info/dependency_links.txt
src/pyramid_tablib.egg-info/not-zip-safe
src/pyramid_tablib.egg-info/requires.txt
src/pyramid_tablib.egg-info/top_level.txt