Metadata-Version: 1.0
Name: pyramid-tablib
Version: 0.2
Summary: tablib renderer (xlsx, xls, csv) for pyramid
Home-page: https://github.com/lxneng/pyramid_tablib
Author: Eric Lo
Author-email: lxneng@gmail.com
License: BSD
Platform: UNKNOWN
